README.md
setup.py
mlstacking/__init__.py
mlstacking/example.py
mlstacking/report.py
mlstacking/sklearn.py
mlstacking.egg-info/PKG-INFO
mlstacking.egg-info/SOURCES.txt
mlstacking.egg-info/dependency_links.txt
mlstacking.egg-info/requires.txt
mlstacking.egg-info/top_level.txt
mlstacking.egg-info/zip-safe