Metadata-Version: 1.1
Name: mlstacking
Version: 0.3.0
Summary: mlstacking is a Python module for sklearn-API friendly multi-layer stacking
Home-page: https://github.com/TalkingData/MultiLayerStacking
Author: HaoWang
Author-email: hao.wang2@tendcloud.com
License: BSD 3-Clause License
Keywords: stacking multi-layer ensemble-learning
Platform: UNKNOWN
Classifier: License :: OSI Approved :: BSD License
Classifier: Programming Language :: Python
Classifier: Intended Audience :: Developers
Classifier: Operating System :: OS Independent
